<?xml version="1.0" encoding="UTF-8"?>

<!-- generated on Sat Jul 13 22:59:54 2019 by SUMO Version 0.32.0
<?xml version="1.0" encoding="UTF-8"?>

<configuration xmlns:xsi="http://www.w3.org/2001/XMLSchema-instance" xsi:noNamespaceSchemaLocation="http://sumo.dlr.de/xsd/sumoConfiguration.xsd">

    <input>
        <net-file value="./comAcostamento/lc2013/base.net.xml"/>
        <route-files value="./comAcostamento/lc2013/base.rou.xml"/>
        <additional-files value="./comAcostamento/lc2013/5660/additional5660.xml"/>
    </input>

    <time>
        <begin value="0"/>
        <end value="5660"/>
    </time>

</configuration>
-->

<meandata xmlns:xsi="http://www.w3.org/2001/XMLSchema-instance" xsi:noNamespaceSchemaLocation="http://sumo.dlr.de/xsd/meandata_file.xsd">
    <interval begin="0.00" end="5660.00" id="myEdges">
        <edge id="1" sampledSeconds="163758.26" traveltime="149.14" overlapTraveltime="153.26" density="145.76" occupancy="35.90" waitingTime="3591.07" speed="1.33" departed="1120" arrived="0" entered="0" left="1073" laneChangedFrom="83" laneChangedTo="83"/>
        <edge id="2" sampledSeconds="315872.29" traveltime="299.01" overlapTraveltime="304.78" density="200.00" occupancy="46.45" waitingTime="51064.56" speed="0.66" departed="0" arrived="0" entered="1073" left="1000" laneChangedFrom="449" laneChangedTo="449"/>
        <edge id="3" sampledSeconds="122197.32" traveltime="117.33" overlapTraveltime="123.69" density="200.00" occupancy="56.37" waitingTime="2747.00" speed="0.78" departed="0" arrived="0" entered="1000" left="978" laneChangedFrom="41" laneChangedTo="41"/>
        <edge id="4" sampledSeconds="32929.11" traveltime="33.33" overlapTraveltime="34.44" density="54.35" occupancy="12.05" waitingTime="0.00" speed="3.25" departed="0" arrived="972" entered="978" left="0" laneChangedFrom="182" laneChangedTo="182"/>
    </interval>
</meandata>
