<?xml version="1.0" encoding="UTF-8"?>

<!-- generated on Fri Aug 16 03:12:09 2019 by SUMO Version 0.28.0
<?xml version="1.0" encoding="UTF-8"?>

<configuration xmlns:xsi="http://www.w3.org/2001/XMLSchema-instance" xsi:noNamespaceSchemaLocation="http://sumo.dlr.de/xsd/sumoConfiguration.xsd">

    <input>
        <net-file value="./comAcostamento/lc2013/base.net.xml"/>
        <route-files value="./comAcostamento/lc2013/base.rou.xml"/>
        <additional-files value="./comAcostamento/lc2013/32880/additional32880.xml"/>
    </input>

    <time>
        <begin value="0"/>
        <end value="32880"/>
    </time>

</configuration>
-->

<meandata xmlns:xsi="http://www.w3.org/2001/XMLSchema-instance" xsi:noNamespaceSchemaLocation="http://sumo.dlr.de/xsd/meandata_file.xsd">
    <interval begin="0.00" end="32880.00" id="myEdges">
        <edge id="1" sampledSeconds="1352267.42" traveltime="230.80" overlapTraveltime="237.21" density="207.19" occupancy="51.80" waitingTime="42914.83" speed="0.86" departed="5870" arrived="0" entered="0" left="5824" laneChangedFrom="199" laneChangedTo="199"/>
        <edge id="2" sampledSeconds="2251536.56" traveltime="382.80" overlapTraveltime="389.04" density="347.60" occupancy="57.93" waitingTime="370976.77" speed="0.52" departed="0" arrived="0" entered="5824" left="5751" laneChangedFrom="1792" laneChangedTo="1792"/>
        <edge id="3" sampledSeconds="739335.12" traveltime="122.46" overlapTraveltime="128.82" density="245.85" occupancy="61.46" waitingTime="16919.00" speed="0.75" departed="0" arrived="0" entered="5750" left="5729" laneChangedFrom="66" laneChangedTo="66"/>
        <edge id="4" sampledSeconds="193894.63" traveltime="33.40" overlapTraveltime="34.52" density="55.09" occupancy="13.77" waitingTime="0.00" speed="3.25" departed="0" arrived="5723" entered="5729" left="0" laneChangedFrom="1121" laneChangedTo="1121"/>
    </interval>
</meandata>
