<?xml version="1.0" encoding="UTF-8"?>

<!-- generated on Mon Aug 19 19:42:58 2019 by SUMO Version 0.28.0
<?xml version="1.0" encoding="UTF-8"?>

<configuration xmlns:xsi="http://www.w3.org/2001/XMLSchema-instance" xsi:noNamespaceSchemaLocation="http://sumo.dlr.de/xsd/sumoConfiguration.xsd">

    <input>
        <net-file value="./comAcostamento/aggressive/base.net.xml"/>
        <route-files value="./comAcostamento/aggressive/base.rou.xml"/>
        <additional-files value="./comAcostamento/aggressive/11500/additional11500.xml"/>
    </input>

    <time>
        <begin value="0"/>
        <end value="11500"/>
    </time>

</configuration>
-->

<meandata xmlns:xsi="http://www.w3.org/2001/XMLSchema-instance" xsi:noNamespaceSchemaLocation="http://sumo.dlr.de/xsd/meandata_file.xsd">
    <interval begin="0.00" end="11500.00" id="myEdges">
        <edge id="1" sampledSeconds="290845.71" traveltime="149.48" overlapTraveltime="153.58" density="127.41" occupancy="31.85" waitingTime="26011.01" speed="1.33" departed="1963" arrived="0" entered="0" left="1924" laneChangedFrom="160" laneChangedTo="160"/>
        <edge id="2" sampledSeconds="549730.13" traveltime="285.01" overlapTraveltime="290.30" density="242.65" occupancy="40.44" waitingTime="150439.73" speed="0.70" departed="0" arrived="0" entered="1924" left="1863" laneChangedFrom="835" laneChangedTo="835"/>
        <edge id="3" sampledSeconds="207177.67" traveltime="105.37" overlapTraveltime="111.73" density="196.98" occupancy="49.24" waitingTime="4774.00" speed="0.86" departed="0" arrived="0" entered="1863" left="1846" laneChangedFrom="70" laneChangedTo="70"/>
        <edge id="4" sampledSeconds="62418.56" traveltime="33.41" overlapTraveltime="34.52" density="50.71" occupancy="12.68" waitingTime="0.00" speed="3.25" departed="0" arrived="1841" entered="1845" left="0" laneChangedFrom="239" laneChangedTo="239"/>
    </interval>
</meandata>
