<?xml version="1.0" encoding="UTF-8"?>

<!-- generated on Thu Aug 15 20:49:56 2019 by SUMO Version 0.28.0
<?xml version="1.0" encoding="UTF-8"?>

<configuration xmlns:xsi="http://www.w3.org/2001/XMLSchema-instance" xsi:noNamespaceSchemaLocation="http://sumo.dlr.de/xsd/sumoConfiguration.xsd">

    <input>
        <net-file value="./comAcostamento/lc2013/base.net.xml"/>
        <route-files value="./comAcostamento/lc2013/base.rou.xml"/>
        <additional-files value="./comAcostamento/lc2013/21180/additional21180.xml"/>
    </input>

    <time>
        <begin value="0"/>
        <end value="21180"/>
    </time>

</configuration>
-->

<meandata xmlns:xsi="http://www.w3.org/2001/XMLSchema-instance" xsi:noNamespaceSchemaLocation="http://sumo.dlr.de/xsd/meandata_file.xsd">
    <interval begin="0.00" end="21180.00" id="myLanes">
        <edge id="1">
            <lane id="1_0" sampledSeconds="400201.45" traveltime="205.51" overlapTraveltime="210.96" density="95.19" occupancy="47.60" waitingTime="16181.28" speed="0.96" departed="1912" arrived="0" entered="0" left="2016" laneChangedFrom="36" laneChangedTo="163"/>
            <lane id="1_1" sampledSeconds="400436.78" traveltime="214.98" overlapTraveltime="221.37" density="95.25" occupancy="47.62" waitingTime="9439.58" speed="0.92" departed="1913" arrived="0" entered="0" left="1762" laneChangedFrom="163" laneChangedTo="36"/>
        </edge>
        <edge id="2">
            <lane id="2_0" sampledSeconds="476040.75" traveltime="421.93" overlapTraveltime="428.77" density="114.09" occupancy="57.05" waitingTime="111018.00" speed="0.47" departed="0" arrived="0" entered="2016" left="980" laneChangedFrom="1033" laneChangedTo="22"/>
            <lane id="2_1" sampledSeconds="461869.14" traveltime="518.92" overlapTraveltime="525.27" density="110.69" occupancy="55.35" waitingTime="108401.00" speed="0.38" departed="0" arrived="0" entered="4" left="924" laneChangedFrom="168" laneChangedTo="1112"/>
            <lane id="2_2" sampledSeconds="450975.68" traveltime="251.78" overlapTraveltime="257.49" density="108.08" occupancy="54.04" waitingTime="12531.25" speed="0.78" departed="0" arrived="0" entered="1758" left="1801" laneChangedFrom="79" laneChangedTo="146"/>
        </edge>
        <edge id="3">
            <lane id="3_0" sampledSeconds="235562.59" traveltime="120.09" overlapTraveltime="126.55" density="121.60" occupancy="60.80" waitingTime="5418.00" speed="0.76" departed="0" arrived="0" entered="1903" left="1829" laneChangedFrom="65" laneChangedTo="1"/>
            <lane id="3_1" sampledSeconds="237104.04" traveltime="123.17" overlapTraveltime="129.46" density="122.40" occupancy="61.20" waitingTime="5534.00" speed="0.75" departed="0" arrived="0" entered="1801" left="1854" laneChangedFrom="1" laneChangedTo="65"/>
        </edge>
        <edge id="4">
            <lane id="4_0" sampledSeconds="70508.42" traveltime="32.18" overlapTraveltime="33.22" density="31.10" occupancy="15.55" waitingTime="0.00" speed="3.37" departed="0" arrived="2542" entered="1828" left="0" laneChangedFrom="0" laneChangedTo="717"/>
            <lane id="4_1" sampledSeconds="54237.88" traveltime="35.22" overlapTraveltime="36.48" density="23.92" occupancy="11.96" waitingTime="0.00" speed="3.07" departed="0" arrived="1134" entered="1854" left="0" laneChangedFrom="717" laneChangedTo="0"/>
        </edge>
    </interval>
</meandata>
