<?xml version="1.0" encoding="UTF-8"?>

<!-- generated on Fri Aug 16 01:52:55 2019 by SUMO Version 0.28.0
<?xml version="1.0" encoding="UTF-8"?>

<configuration xmlns:xsi="http://www.w3.org/2001/XMLSchema-instance" xsi:noNamespaceSchemaLocation="http://sumo.dlr.de/xsd/sumoConfiguration.xsd">

    <input>
        <net-file value="./comAcostamento/lc2013/base.net.xml"/>
        <route-files value="./comAcostamento/lc2013/base.rou.xml"/>
        <additional-files value="./comAcostamento/lc2013/30740/additional30740.xml"/>
    </input>

    <time>
        <begin value="0"/>
        <end value="30740"/>
    </time>

</configuration>
-->

<meandata xmlns:xsi="http://www.w3.org/2001/XMLSchema-instance" xsi:noNamespaceSchemaLocation="http://sumo.dlr.de/xsd/meandata_file.xsd">
    <interval begin="0.00" end="30740.00" id="myEdges">
        <edge id="1" sampledSeconds="1251389.20" traveltime="228.12" overlapTraveltime="234.48" density="205.08" occupancy="51.27" waitingTime="39785.65" speed="0.87" departed="5499" arrived="0" entered="0" left="5451" laneChangedFrom="199" laneChangedTo="199"/>
        <edge id="2" sampledSeconds="2093713.15" traveltime="380.44" overlapTraveltime="386.67" density="345.74" occupancy="57.62" waitingTime="345244.77" speed="0.52" departed="0" arrived="0" entered="5451" left="5379" laneChangedFrom="1698" laneChangedTo="1698"/>
        <edge id="3" sampledSeconds="690481.74" traveltime="122.29" overlapTraveltime="128.66" density="245.59" occupancy="61.40" waitingTime="15773.00" speed="0.75" departed="0" arrived="0" entered="5378" left="5356" laneChangedFrom="66" laneChangedTo="66"/>
        <edge id="4" sampledSeconds="181245.30" traveltime="33.39" overlapTraveltime="34.51" density="55.08" occupancy="13.77" waitingTime="0.00" speed="3.25" departed="0" arrived="5350" entered="5356" left="0" laneChangedFrom="1050" laneChangedTo="1050"/>
    </interval>
</meandata>
