<?xml version="1.0" encoding="UTF-8"?>

<!-- generated on Fri Aug 16 00:29:49 2019 by SUMO Version 0.28.0
<?xml version="1.0" encoding="UTF-8"?>

<configuration xmlns:xsi="http://www.w3.org/2001/XMLSchema-instance" xsi:noNamespaceSchemaLocation="http://sumo.dlr.de/xsd/sumoConfiguration.xsd">

    <input>
        <net-file value="./comAcostamento/lc2013/base.net.xml"/>
        <route-files value="./comAcostamento/lc2013/base.rou.xml"/>
        <additional-files value="./comAcostamento/lc2013/28220/additional28220.xml"/>
    </input>

    <time>
        <begin value="0"/>
        <end value="28220"/>
    </time>

</configuration>
-->

<meandata xmlns:xsi="http://www.w3.org/2001/XMLSchema-instance" xsi:noNamespaceSchemaLocation="http://sumo.dlr.de/xsd/meandata_file.xsd">
    <interval begin="0.00" end="28220.00" id="myLanes">
        <edge id="1">
            <lane id="1_0" sampledSeconds="565826.04" traveltime="220.61" overlapTraveltime="226.47" density="101.01" occupancy="50.51" waitingTime="22805.41" speed="0.90" departed="2529" arrived="0" entered="0" left="2634" laneChangedFrom="36" laneChangedTo="163"/>
            <lane id="1_1" sampledSeconds="566825.15" traveltime="228.58" overlapTraveltime="235.28" density="101.19" occupancy="50.59" waitingTime="13189.00" speed="0.86" departed="2528" arrived="0" entered="0" left="2378" laneChangedFrom="163" laneChangedTo="36"/>
        </edge>
        <edge id="2">
            <lane id="2_0" sampledSeconds="652326.14" traveltime="452.06" overlapTraveltime="458.99" density="117.34" occupancy="58.67" waitingTime="150530.00" speed="0.44" departed="0" arrived="0" entered="2633" left="1288" laneChangedFrom="1342" laneChangedTo="22"/>
            <lane id="2_1" sampledSeconds="634799.85" traveltime="529.07" overlapTraveltime="535.54" density="114.19" occupancy="57.09" waitingTime="148323.00" speed="0.38" departed="0" arrived="0" entered="4" left="1233" laneChangedFrom="168" laneChangedTo="1421"/>
            <lane id="2_2" sampledSeconds="620784.95" traveltime="256.44" overlapTraveltime="262.20" density="111.67" occupancy="55.83" waitingTime="16647.25" speed="0.77" departed="0" arrived="0" entered="2374" left="2418" laneChangedFrom="79" laneChangedTo="146"/>
        </edge>
        <edge id="3">
            <lane id="3_0" sampledSeconds="315263.65" traveltime="120.77" overlapTraveltime="127.20" density="122.15" occupancy="61.07" waitingTime="7130.00" speed="0.76" departed="0" arrived="0" entered="2520" left="2445" laneChangedFrom="65" laneChangedTo="1"/>
            <lane id="3_1" sampledSeconds="317844.39" traveltime="123.56" overlapTraveltime="129.86" density="123.15" occupancy="61.57" waitingTime="7413.00" speed="0.74" departed="0" arrived="0" entered="2417" left="2470" laneChangedFrom="1" laneChangedTo="65"/>
        </edge>
        <edge id="4">
            <lane id="4_0" sampledSeconds="93964.57" traveltime="32.08" overlapTraveltime="33.10" density="31.11" occupancy="15.55" waitingTime="0.00" speed="3.38" departed="0" arrived="3405" entered="2445" left="0" laneChangedFrom="0" laneChangedTo="963"/>
            <lane id="4_1" sampledSeconds="72413.82" traveltime="35.28" overlapTraveltime="36.54" density="23.97" occupancy="11.99" waitingTime="0.00" speed="3.07" departed="0" arrived="1506" entered="2470" left="0" laneChangedFrom="963" laneChangedTo="0"/>
        </edge>
    </interval>
</meandata>
