<?xml version="1.0" encoding="UTF-8"?>

<!-- generated on Sat Aug 17 23:45:41 2019 by SUMO Version 0.28.0
<?xml version="1.0" encoding="UTF-8"?>

<configuration xmlns:xsi="http://www.w3.org/2001/XMLSchema-instance" xsi:noNamespaceSchemaLocation="http://sumo.dlr.de/xsd/sumoConfiguration.xsd">

    <input>
        <net-file value="./comAcostamento/lc2013/base.net.xml"/>
        <route-files value="./comAcostamento/lc2013/base.rou.xml"/>
        <additional-files value="./comAcostamento/lc2013/69600/additional69600.xml"/>
    </input>

    <time>
        <begin value="0"/>
        <end value="69600"/>
    </time>

</configuration>
-->

<meandata xmlns:xsi="http://www.w3.org/2001/XMLSchema-instance" xsi:noNamespaceSchemaLocation="http://sumo.dlr.de/xsd/meandata_file.xsd">
    <interval begin="0.00" end="69600.00" id="myLanes">
        <edge id="1">
            <lane id="1_0" sampledSeconds="1538316.09" traveltime="248.86" overlapTraveltime="255.47" density="111.35" occupancy="55.67" waitingTime="64020.62" speed="0.80" departed="6145" arrived="0" entered="0" left="6246" laneChangedFrom="39" laneChangedTo="163"/>
            <lane id="1_1" sampledSeconds="1543432.73" traveltime="253.04" overlapTraveltime="260.26" density="111.72" occupancy="55.86" waitingTime="35788.25" speed="0.78" departed="6137" arrived="0" entered="0" left="5990" laneChangedFrom="163" laneChangedTo="39"/>
        </edge>
        <edge id="2">
            <lane id="2_0" sampledSeconds="1688915.77" traveltime="513.88" overlapTraveltime="520.89" density="123.18" occupancy="61.59" waitingTime="387117.98" speed="0.39" departed="0" arrived="0" entered="6246" left="3095" laneChangedFrom="3149" laneChangedTo="22"/>
            <lane id="2_1" sampledSeconds="1651361.91" traveltime="547.91" overlapTraveltime="554.59" density="120.44" occupancy="60.22" waitingTime="379950.00" speed="0.36" departed="0" arrived="0" entered="4" left="3039" laneChangedFrom="168" laneChangedTo="3228"/>
            <lane id="2_2" sampledSeconds="1619148.17" traveltime="264.97" overlapTraveltime="270.80" density="118.09" occupancy="59.04" waitingTime="43888.91" speed="0.75" departed="0" arrived="0" entered="5986" left="6029" laneChangedFrom="79" laneChangedTo="146"/>
        </edge>
        <edge id="3">
            <lane id="3_0" sampledSeconds="783838.51" traveltime="122.28" overlapTraveltime="128.67" density="123.14" occupancy="61.57" waitingTime="17798.00" speed="0.75" departed="0" arrived="0" entered="6133" left="6059" laneChangedFrom="65" laneChangedTo="1"/>
            <lane id="3_1" sampledSeconds="792234.84" traveltime="124.41" overlapTraveltime="130.75" density="124.46" occupancy="62.23" waitingTime="18210.00" speed="0.74" departed="0" arrived="0" entered="6029" left="6082" laneChangedFrom="1" laneChangedTo="65"/>
        </edge>
        <edge id="4">
            <lane id="4_0" sampledSeconds="231378.75" traveltime="31.95" overlapTraveltime="32.97" density="31.06" occupancy="15.53" waitingTime="0.00" speed="3.40" departed="0" arrived="8433" entered="6059" left="0" laneChangedFrom="0" laneChangedTo="2377"/>
            <lane id="4_1" sampledSeconds="179706.02" traveltime="35.47" overlapTraveltime="36.75" density="24.12" occupancy="12.06" waitingTime="0.00" speed="3.05" departed="0" arrived="3702" entered="6082" left="0" laneChangedFrom="2377" laneChangedTo="0"/>
        </edge>
    </interval>
</meandata>
