<?xml version="1.0" encoding="UTF-8"?>

<!-- generated on Fri Aug 16 08:05:00 2019 by SUMO Version 0.28.0
<?xml version="1.0" encoding="UTF-8"?>

<configuration xmlns:xsi="http://www.w3.org/2001/XMLSchema-instance" xsi:noNamespaceSchemaLocation="http://sumo.dlr.de/xsd/sumoConfiguration.xsd">

    <input>
        <net-file value="./comAcostamento/lc2013/base.net.xml"/>
        <route-files value="./comAcostamento/lc2013/base.rou.xml"/>
        <additional-files value="./comAcostamento/lc2013/39400/additional39400.xml"/>
    </input>

    <time>
        <begin value="0"/>
        <end value="39400"/>
    </time>

</configuration>
-->

<meandata xmlns:xsi="http://www.w3.org/2001/XMLSchema-instance" xsi:noNamespaceSchemaLocation="http://sumo.dlr.de/xsd/meandata_file.xsd">
    <interval begin="0.00" end="39400.00" id="myLanes">
        <edge id="1">
            <lane id="1_0" sampledSeconds="828699.78" traveltime="234.04" overlapTraveltime="240.24" density="105.96" occupancy="52.98" waitingTime="33843.02" speed="0.85" departed="3504" arrived="0" entered="0" left="3608" laneChangedFrom="36" laneChangedTo="163"/>
            <lane id="1_1" sampledSeconds="830674.06" traveltime="240.33" overlapTraveltime="247.29" density="106.21" occupancy="53.11" waitingTime="19368.18" speed="0.82" departed="3503" arrived="0" entered="0" left="3352" laneChangedFrom="163" laneChangedTo="36"/>
        </edge>
        <edge id="2">
            <lane id="2_0" sampledSeconds="932400.41" traveltime="480.44" overlapTraveltime="487.43" density="120.13" occupancy="60.06" waitingTime="214356.00" speed="0.41" departed="0" arrived="0" entered="3608" left="1776" laneChangedFrom="1830" laneChangedTo="22"/>
            <lane id="2_1" sampledSeconds="909450.72" traveltime="538.27" overlapTraveltime="544.84" density="117.17" occupancy="58.59" waitingTime="211046.00" speed="0.37" departed="0" arrived="0" entered="4" left="1720" laneChangedFrom="168" laneChangedTo="1909"/>
            <lane id="2_2" sampledSeconds="890576.03" traveltime="260.69" overlapTraveltime="266.48" density="114.74" occupancy="57.37" waitingTime="24053.10" speed="0.76" departed="0" arrived="0" entered="3348" left="3392" laneChangedFrom="79" laneChangedTo="146"/>
        </edge>
        <edge id="3">
            <lane id="3_0" sampledSeconds="441907.85" traveltime="121.53" overlapTraveltime="127.94" density="122.63" occupancy="61.32" waitingTime="10038.00" speed="0.75" departed="0" arrived="0" entered="3496" left="3421" laneChangedFrom="65" laneChangedTo="1"/>
            <lane id="3_1" sampledSeconds="446017.57" traveltime="124.01" overlapTraveltime="130.33" density="123.77" occupancy="61.89" waitingTime="10376.00" speed="0.74" departed="0" arrived="0" entered="3392" left="3445" laneChangedFrom="1" laneChangedTo="65"/>
        </edge>
        <edge id="4">
            <lane id="4_0" sampledSeconds="131268.96" traveltime="31.97" overlapTraveltime="32.99" density="31.13" occupancy="15.56" waitingTime="0.00" speed="3.40" departed="0" arrived="4783" entered="3421" left="0" laneChangedFrom="0" laneChangedTo="1366"/>
            <lane id="4_1" sampledSeconds="101130.81" traveltime="35.44" overlapTraveltime="36.72" density="23.98" occupancy="11.99" waitingTime="0.00" speed="3.05" departed="0" arrived="2077" entered="3445" left="0" laneChangedFrom="1366" laneChangedTo="0"/>
        </edge>
    </interval>
</meandata>
