<?xml version="1.0" encoding="UTF-8"?>

<!-- generated on Sun Jul 14 18:17:14 2019 by SUMO Version 0.32.0
<?xml version="1.0" encoding="UTF-8"?>

<configuration xmlns:xsi="http://www.w3.org/2001/XMLSchema-instance" xsi:noNamespaceSchemaLocation="http://sumo.dlr.de/xsd/sumoConfiguration.xsd">

    <input>
        <net-file value="./semAcostamento/lc2013/base.net.xml"/>
        <route-files value="./semAcostamento/lc2013/base.rou.xml"/>
        <additional-files value="./semAcostamento/lc2013/80/additional80.xml"/>
    </input>

    <time>
        <begin value="0"/>
        <end value="80"/>
    </time>

</configuration>
-->

<meandata xmlns:xsi="http://www.w3.org/2001/XMLSchema-instance" xsi:noNamespaceSchemaLocation="http://sumo.dlr.de/xsd/meandata_file.xsd">
    <interval begin="0.00" end="80.00" id="myLanes">
        <edge id="1">
            <lane id="1_0" sampledSeconds="328.27" traveltime="51.25" overlapTraveltime="52.01" density="20.52" occupancy="10.21" waitingTime="0.00" speed="3.94" departed="9" arrived="0" entered="0" left="5" laneChangedFrom="0" laneChangedTo="2"/>
            <lane id="1_1" sampledSeconds="259.04" traveltime="61.52" overlapTraveltime="62.60" density="16.19" occupancy="8.08" waitingTime="0.00" speed="3.28" departed="9" arrived="0" entered="0" left="2" laneChangedFrom="2" laneChangedTo="0"/>
        </edge>
        <edge id="2">
            <lane id="2_0" sampledSeconds="77.15" traveltime="21.20" overlapTraveltime="21.68" density="4.82" occupancy="2.35" waitingTime="0.00" speed="9.45" departed="0" arrived="0" entered="5" left="2" laneChangedFrom="0" laneChangedTo="0"/>
            <lane id="2_1" sampledSeconds="26.12" traveltime="19.40" overlapTraveltime="19.81" density="1.63" occupancy="0.79" waitingTime="0.00" speed="10.35" departed="0" arrived="0" entered="2" left="1" laneChangedFrom="0" laneChangedTo="0"/>
        </edge>
        <edge id="3">
            <lane id="3_0" sampledSeconds="20.30" traveltime="9.77" overlapTraveltime="13.57" density="2.73" occupancy="1.19" waitingTime="1.00" speed="7.22" departed="0" arrived="0" entered="2" left="1" laneChangedFrom="0" laneChangedTo="1"/>
            <lane id="3_1" sampledSeconds="7.37" traveltime="7.53" overlapTraveltime="7.94" density="0.99" occupancy="0.48" waitingTime="0.00" speed="12.34" departed="0" arrived="0" entered="1" left="0" laneChangedFrom="1" laneChangedTo="0"/>
        </edge>
        <edge id="4">
            <lane id="4_0" sampledSeconds="10.26" traveltime="72.30" overlapTraveltime="75.68" density="1.20" occupancy="0.42" waitingTime="0.00" speed="1.48" departed="0" arrived="0" entered="1" left="0" laneChangedFrom="0" laneChangedTo="0"/>
            <lane id="4_1" sampledSeconds="0.00" departed="0" arrived="0" entered="0" left="0" laneChangedFrom="0" laneChangedTo="0"/>
        </edge>
    </interval>
</meandata>
