<?xml version="1.0" encoding="UTF-8"?>

<!-- generated on Fri Aug 16 06:56:23 2019 by SUMO Version 0.28.0
<?xml version="1.0" encoding="UTF-8"?>

<configuration xmlns:xsi="http://www.w3.org/2001/XMLSchema-instance" xsi:noNamespaceSchemaLocation="http://sumo.dlr.de/xsd/sumoConfiguration.xsd">

    <input>
        <net-file value="./comAcostamento/lc2013/base.net.xml"/>
        <route-files value="./comAcostamento/lc2013/base.rou.xml"/>
        <additional-files value="./comAcostamento/lc2013/38020/additional38020.xml"/>
    </input>

    <time>
        <begin value="0"/>
        <end value="38020"/>
    </time>

</configuration>
-->

<meandata xmlns:xsi="http://www.w3.org/2001/XMLSchema-instance" xsi:noNamespaceSchemaLocation="http://sumo.dlr.de/xsd/meandata_file.xsd">
    <interval begin="0.00" end="38020.00" id="myLanes">
        <edge id="1">
            <lane id="1_0" sampledSeconds="796361.08" traveltime="232.88" overlapTraveltime="239.04" density="105.52" occupancy="52.76" waitingTime="32451.99" speed="0.85" departed="3383" arrived="0" entered="0" left="3488" laneChangedFrom="36" laneChangedTo="163"/>
            <lane id="1_1" sampledSeconds="797956.93" traveltime="239.14" overlapTraveltime="246.07" density="105.73" occupancy="52.87" waitingTime="18646.18" speed="0.83" departed="3383" arrived="0" entered="0" left="3233" laneChangedFrom="163" laneChangedTo="36"/>
        </edge>
        <edge id="2">
            <lane id="2_0" sampledSeconds="897855.00" traveltime="477.85" overlapTraveltime="484.84" density="119.87" occupancy="59.94" waitingTime="206519.00" speed="0.42" departed="0" arrived="0" entered="3487" left="1715" laneChangedFrom="1769" laneChangedTo="22"/>
            <lane id="2_1" sampledSeconds="875569.65" traveltime="537.59" overlapTraveltime="544.14" density="116.90" occupancy="58.45" waitingTime="203342.00" speed="0.37" departed="0" arrived="0" entered="4" left="1660" laneChangedFrom="168" laneChangedTo="1848"/>
            <lane id="2_2" sampledSeconds="857254.60" traveltime="260.24" overlapTraveltime="266.03" density="114.45" occupancy="57.23" waitingTime="23059.77" speed="0.76" departed="0" arrived="0" entered="3229" left="3272" laneChangedFrom="79" laneChangedTo="146"/>
        </edge>
        <edge id="3">
            <lane id="3_0" sampledSeconds="426275.80" traveltime="121.50" overlapTraveltime="127.91" density="122.59" occupancy="61.29" waitingTime="9702.00" speed="0.75" departed="0" arrived="0" entered="3375" left="3300" laneChangedFrom="65" laneChangedTo="1"/>
            <lane id="3_1" sampledSeconds="430213.78" traveltime="123.95" overlapTraveltime="130.27" density="123.72" occupancy="61.86" waitingTime="9986.00" speed="0.74" departed="0" arrived="0" entered="3272" left="3325" laneChangedFrom="1" laneChangedTo="65"/>
        </edge>
        <edge id="4">
            <lane id="4_0" sampledSeconds="126559.28" traveltime="31.99" overlapTraveltime="33.02" density="31.10" occupancy="15.55" waitingTime="0.00" speed="3.39" departed="0" arrived="4605" entered="3300" left="0" laneChangedFrom="0" laneChangedTo="1309"/>
            <lane id="4_1" sampledSeconds="97664.25" traveltime="35.40" overlapTraveltime="36.68" density="24.00" occupancy="12.00" waitingTime="0.00" speed="3.05" departed="0" arrived="2014" entered="3325" left="0" laneChangedFrom="1309" laneChangedTo="0"/>
        </edge>
    </interval>
</meandata>
