<?xml version="1.0" encoding="UTF-8"?>

<!-- generated on Sat Jul 13 23:12:11 2019 by SUMO Version 0.32.0
<?xml version="1.0" encoding="UTF-8"?>

<configuration xmlns:xsi="http://www.w3.org/2001/XMLSchema-instance" xsi:noNamespaceSchemaLocation="http://sumo.dlr.de/xsd/sumoConfiguration.xsd">

    <input>
        <net-file value="./comAcostamento/lc2013/base.net.xml"/>
        <route-files value="./comAcostamento/lc2013/base.rou.xml"/>
        <additional-files value="./comAcostamento/lc2013/7940/additional7940.xml"/>
    </input>

    <time>
        <begin value="0"/>
        <end value="7940"/>
    </time>

</configuration>
-->

<meandata xmlns:xsi="http://www.w3.org/2001/XMLSchema-instance" xsi:noNamespaceSchemaLocation="http://sumo.dlr.de/xsd/meandata_file.xsd">
    <interval begin="0.00" end="7940.00" id="myLanes">
        <edge id="1">
            <lane id="1_0" sampledSeconds="135994.73" traveltime="177.77" overlapTraveltime="182.26" density="86.29" occupancy="42.53" waitingTime="3661.23" speed="1.12" departed="757" arrived="0" entered="0" left="781" laneChangedFrom="18" laneChangedTo="65"/>
            <lane id="1_1" sampledSeconds="135960.38" traveltime="186.33" overlapTraveltime="191.80" density="86.26" occupancy="42.48" waitingTime="2669.98" speed="1.06" departed="759" arrived="0" entered="0" left="689" laneChangedFrom="65" laneChangedTo="18"/>
        </edge>
        <edge id="2">
            <lane id="2_0" sampledSeconds="166239.05" traveltime="360.48" overlapTraveltime="366.79" density="106.28" occupancy="52.35" waitingTime="38571.00" speed="0.55" departed="0" arrived="0" entered="781" left="389" laneChangedFrom="390" laneChangedTo="23"/>
            <lane id="2_1" sampledSeconds="161041.15" traveltime="479.21" overlapTraveltime="485.37" density="102.96" occupancy="51.02" waitingTime="36221.00" speed="0.42" departed="0" arrived="0" entered="1" left="347" laneChangedFrom="89" laneChangedTo="459"/>
            <lane id="2_2" sampledSeconds="156963.10" traveltime="236.74" overlapTraveltime="242.42" density="100.35" occupancy="48.93" waitingTime="3864.32" speed="0.83" departed="0" arrived="0" entered="688" left="661" laneChangedFrom="69" laneChangedTo="66"/>
        </edge>
        <edge id="3">
            <lane id="3_0" sampledSeconds="86938.38" traveltime="117.60" overlapTraveltime="124.05" density="119.72" occupancy="57.39" waitingTime="2000.00" speed="0.78" departed="0" arrived="0" entered="734" left="682" laneChangedFrom="41" laneChangedTo="0"/>
            <lane id="3_1" sampledSeconds="87269.92" traveltime="121.45" overlapTraveltime="127.71" density="120.17" occupancy="57.17" waitingTime="1914.00" speed="0.76" departed="0" arrived="0" entered="662" left="692" laneChangedFrom="0" laneChangedTo="41"/>
        </edge>
        <edge id="4">
            <lane id="4_0" sampledSeconds="26440.00" traveltime="32.11" overlapTraveltime="33.14" density="31.11" occupancy="13.98" waitingTime="0.00" speed="3.38" departed="0" arrived="935" entered="682" left="0" laneChangedFrom="1" laneChangedTo="258"/>
            <lane id="4_1" sampledSeconds="19854.74" traveltime="35.06" overlapTraveltime="36.29" density="23.36" occupancy="10.18" waitingTime="0.00" speed="3.09" departed="0" arrived="433" entered="692" left="0" laneChangedFrom="258" laneChangedTo="1"/>
        </edge>
    </interval>
</meandata>
