<?xml version="1.0" encoding="UTF-8"?>

<!-- generated on Sat Aug 17 23:25:03 2019 by SUMO Version 0.28.0
<?xml version="1.0" encoding="UTF-8"?>

<configuration xmlns:xsi="http://www.w3.org/2001/XMLSchema-instance" xsi:noNamespaceSchemaLocation="http://sumo.dlr.de/xsd/sumoConfiguration.xsd">

    <input>
        <net-file value="./comAcostamento/lc2013/base.net.xml"/>
        <route-files value="./comAcostamento/lc2013/base.rou.xml"/>
        <additional-files value="./comAcostamento/lc2013/69460/additional69460.xml"/>
    </input>

    <time>
        <begin value="0"/>
        <end value="69460"/>
    </time>

</configuration>
-->

<meandata xmlns:xsi="http://www.w3.org/2001/XMLSchema-instance" xsi:noNamespaceSchemaLocation="http://sumo.dlr.de/xsd/meandata_file.xsd">
    <interval begin="0.00" end="69460.00" id="myLanes">
        <edge id="1">
            <lane id="1_0" sampledSeconds="1535014.34" traveltime="248.82" overlapTraveltime="255.42" density="111.33" occupancy="55.67" waitingTime="63844.62" speed="0.80" departed="6134" arrived="0" entered="0" left="6234" laneChangedFrom="39" laneChangedTo="163"/>
            <lane id="1_1" sampledSeconds="1540152.54" traveltime="253.02" overlapTraveltime="260.24" density="111.70" occupancy="55.85" waitingTime="35740.25" speed="0.78" departed="6124" arrived="0" entered="0" left="5978" laneChangedFrom="163" laneChangedTo="39"/>
        </edge>
        <edge id="2">
            <lane id="2_0" sampledSeconds="1685399.80" traveltime="513.76" overlapTraveltime="520.78" density="123.17" occupancy="61.58" waitingTime="386362.98" speed="0.39" departed="0" arrived="0" entered="6234" left="3089" laneChangedFrom="3143" laneChangedTo="22"/>
            <lane id="2_1" sampledSeconds="1647920.66" traveltime="547.85" overlapTraveltime="554.54" density="120.43" occupancy="60.22" waitingTime="379152.00" speed="0.36" departed="0" arrived="0" entered="4" left="3033" laneChangedFrom="168" laneChangedTo="3222"/>
            <lane id="2_2" sampledSeconds="1615765.05" traveltime="264.95" overlapTraveltime="270.78" density="118.08" occupancy="59.04" waitingTime="43844.91" speed="0.75" departed="0" arrived="0" entered="5973" left="6017" laneChangedFrom="79" laneChangedTo="146"/>
        </edge>
        <edge id="3">
            <lane id="3_0" sampledSeconds="782253.53" traveltime="122.27" overlapTraveltime="128.67" density="123.14" occupancy="61.57" waitingTime="17749.00" speed="0.75" departed="0" arrived="0" entered="6122" left="6047" laneChangedFrom="65" laneChangedTo="1"/>
            <lane id="3_1" sampledSeconds="790624.85" traveltime="124.40" overlapTraveltime="130.74" density="124.45" occupancy="62.23" waitingTime="18173.00" speed="0.74" departed="0" arrived="0" entered="6017" left="6070" laneChangedFrom="1" laneChangedTo="65"/>
        </edge>
        <edge id="4">
            <lane id="4_0" sampledSeconds="230932.27" traveltime="31.94" overlapTraveltime="32.97" density="31.06" occupancy="15.53" waitingTime="0.00" speed="3.40" departed="0" arrived="8417" entered="6047" left="0" laneChangedFrom="0" laneChangedTo="2373"/>
            <lane id="4_1" sampledSeconds="179320.21" traveltime="35.47" overlapTraveltime="36.76" density="24.12" occupancy="12.06" waitingTime="0.00" speed="3.05" departed="0" arrived="3694" entered="6070" left="0" laneChangedFrom="2373" laneChangedTo="0"/>
        </edge>
    </interval>
</meandata>
