<?xml version="1.0" encoding="UTF-8"?>

<!-- generated on Thu Aug 15 18:52:46 2019 by SUMO Version 0.28.0
<?xml version="1.0" encoding="UTF-8"?>

<configuration xmlns:xsi="http://www.w3.org/2001/XMLSchema-instance" xsi:noNamespaceSchemaLocation="http://sumo.dlr.de/xsd/sumoConfiguration.xsd">

    <input>
        <net-file value="./comAcostamento/lc2013/base.net.xml"/>
        <route-files value="./comAcostamento/lc2013/base.rou.xml"/>
        <additional-files value="./comAcostamento/lc2013/8140/additional8140.xml"/>
    </input>

    <time>
        <begin value="0"/>
        <end value="8140"/>
    </time>

</configuration>
-->

<meandata xmlns:xsi="http://www.w3.org/2001/XMLSchema-instance" xsi:noNamespaceSchemaLocation="http://sumo.dlr.de/xsd/meandata_file.xsd">
    <interval begin="0.00" end="8140.00" id="myLanes">
        <edge id="1">
            <lane id="1_0" sampledSeconds="93983.04" traveltime="116.06" overlapTraveltime="119.30" density="58.17" occupancy="29.08" waitingTime="3266.62" speed="1.71" departed="774" arrived="0" entered="0" left="879" laneChangedFrom="35" laneChangedTo="163"/>
            <lane id="1_1" sampledSeconds="92653.39" traveltime="128.34" overlapTraveltime="132.58" density="57.34" occupancy="28.67" waitingTime="2181.11" speed="1.53" departed="775" arrived="0" entered="0" left="624" laneChangedFrom="163" laneChangedTo="35"/>
        </edge>
        <edge id="2">
            <lane id="2_0" sampledSeconds="149321.49" traveltime="272.18" overlapTraveltime="278.02" density="93.12" occupancy="46.56" waitingTime="35215.00" speed="0.73" departed="0" arrived="0" entered="878" left="411" laneChangedFrom="465" laneChangedTo="22"/>
            <lane id="2_1" sampledSeconds="141440.00" traveltime="443.14" overlapTraveltime="448.80" density="88.20" occupancy="44.10" waitingTime="33914.00" speed="0.45" departed="0" arrived="0" entered="4" left="355" laneChangedFrom="168" laneChangedTo="544"/>
            <lane id="2_2" sampledSeconds="136326.96" traveltime="217.05" overlapTraveltime="222.56" density="85.01" occupancy="42.51" waitingTime="4477.08" speed="0.91" departed="0" arrived="0" entered="619" left="663" laneChangedFrom="79" laneChangedTo="146"/>
        </edge>
        <edge id="3">
            <lane id="3_0" sampledSeconds="87895.28" traveltime="114.85" overlapTraveltime="121.41" density="118.06" occupancy="59.03" waitingTime="2046.00" speed="0.79" departed="0" arrived="0" entered="766" left="691" laneChangedFrom="65" laneChangedTo="1"/>
            <lane id="3_1" sampledSeconds="87582.22" traveltime="120.22" overlapTraveltime="126.40" density="117.64" occupancy="58.82" waitingTime="2064.00" speed="0.76" departed="0" arrived="0" entered="662" left="716" laneChangedFrom="1" laneChangedTo="65"/>
        </edge>
        <edge id="4">
            <lane id="4_0" sampledSeconds="26985.40" traveltime="32.67" overlapTraveltime="33.73" density="30.97" occupancy="15.49" waitingTime="0.00" speed="3.32" departed="0" arrived="946" entered="691" left="0" laneChangedFrom="0" laneChangedTo="258"/>
            <lane id="4_1" sampledSeconds="20573.79" traveltime="34.53" overlapTraveltime="35.76" density="23.61" occupancy="11.81" waitingTime="0.00" speed="3.13" departed="0" arrived="454" entered="716" left="0" laneChangedFrom="258" laneChangedTo="0"/>
        </edge>
    </interval>
</meandata>
