<?xml version="1.0" encoding="UTF-8"?>

<!-- generated on Thu Aug 15 22:04:10 2019 by SUMO Version 0.28.0
<?xml version="1.0" encoding="UTF-8"?>

<configuration xmlns:xsi="http://www.w3.org/2001/XMLSchema-instance" xsi:noNamespaceSchemaLocation="http://sumo.dlr.de/xsd/sumoConfiguration.xsd">

    <input>
        <net-file value="./semAcostamento/lc2013/base.net.xml"/>
        <route-files value="./semAcostamento/lc2013/base.rou.xml"/>
        <additional-files value="./semAcostamento/lc2013/24620/additional24620.xml"/>
    </input>

    <time>
        <begin value="0"/>
        <end value="24620"/>
    </time>

</configuration>
-->

<meandata xmlns:xsi="http://www.w3.org/2001/XMLSchema-instance" xsi:noNamespaceSchemaLocation="http://sumo.dlr.de/xsd/meandata_file.xsd">
    <interval begin="0.00" end="24620.00" id="myEdges">
        <edge id="1" sampledSeconds="1010662.69" traveltime="230.89" overlapTraveltime="236.85" density="205.25" occupancy="51.31" waitingTime="12487.00" speed="0.87" departed="4400" arrived="0" entered="0" left="4353" laneChangedFrom="155" laneChangedTo="155"/>
        <edge id="2" sampledSeconds="1112965.22" traveltime="249.80" overlapTraveltime="257.10" density="226.03" occupancy="56.51" waitingTime="9867.27" speed="0.80" departed="0" arrived="0" entered="4353" left="4306" laneChangedFrom="128" laneChangedTo="128"/>
        <edge id="3" sampledSeconds="560508.13" traveltime="124.16" overlapTraveltime="130.53" density="244.91" occupancy="61.23" waitingTime="12964.00" speed="0.75" departed="0" arrived="0" entered="4306" left="4283" laneChangedFrom="30" laneChangedTo="30"/>
        <edge id="4" sampledSeconds="144909.78" traveltime="33.39" overlapTraveltime="34.51" density="54.99" occupancy="13.75" waitingTime="0.00" speed="3.25" departed="0" arrived="4277" entered="4283" left="0" laneChangedFrom="429" laneChangedTo="429"/>
    </interval>
</meandata>
