<?xml version="1.0" encoding="UTF-8"?>

<!-- generated on Thu Apr 16 21:58:44 2020 by SUMO Version 0.32.0
<?xml version="1.0" encoding="UTF-8"?>

<configuration xmlns:xsi="http://www.w3.org/2001/XMLSchema-instance" xsi:noNamespaceSchemaLocation="http://sumo.dlr.de/xsd/sumoConfiguration.xsd">

    <input>
        <net-file value="base.net.xml"/>
        <route-files value="base.rou.xml"/>
        <additional-files value="additional.xml"/>
    </input>

    <time>
        <begin value="0"/>
        <end value="50000"/>
    </time>

    <random_number>
        <seed value="42069"/>
    </random_number>

</configuration>
-->

<detector xmlns:xsi="http://www.w3.org/2001/XMLSchema-instance" xsi:noNamespaceSchemaLocation="http://sumo.dlr.de/xsd/det_e2_file.xsd">
   <interval begin="0.00" end="50000.00" id="bot" sampledSeconds="1279053.31" nVehEntered="5060" nVehLeft="5046" nVehSeen="5060" meanSpeed="3.92" meanTimeLoss="181.53" meanOccupancy="10.14" maxOccupancy="42.53" meanMaxJamLengthInVehicles="1.71" meanMaxJamLengthInMeters="9.78" maxJamLengthInVehicles="21" maxJamLengthInMeters="155.11" jamLengthInVehiclesSum="179288" jamLengthInMetersSum="887976.53" meanHaltingDuration="1.47" maxHaltingDuration="36.00" haltingDurationSum="560944.00" meanIntervalHaltingDuration="1.47" maxIntervalHaltingDuration="36.00" intervalHaltingDurationSum="560944.00" startedHalts="381659.00" meanVehicleNumber="25.67" maxVehicleNumber="107" />
</detector>
