<?xml version="1.0" encoding="UTF-8"?>

<!-- generated on Sun Jul 14 18:26:04 2019 by SUMO Version 0.32.0
<?xml version="1.0" encoding="UTF-8"?>

<configuration xmlns:xsi="http://www.w3.org/2001/XMLSchema-instance" xsi:noNamespaceSchemaLocation="http://sumo.dlr.de/xsd/sumoConfiguration.xsd">

    <input>
        <net-file value="./semAcostamento/lc2013/base.net.xml"/>
        <route-files value="./semAcostamento/lc2013/base.rou.xml"/>
        <additional-files value="./semAcostamento/lc2013/7360/additional7360.xml"/>
    </input>

    <time>
        <begin value="0"/>
        <end value="7360"/>
    </time>

</configuration>
-->

<meandata xmlns:xsi="http://www.w3.org/2001/XMLSchema-instance" xsi:noNamespaceSchemaLocation="http://sumo.dlr.de/xsd/meandata_file.xsd">
    <interval begin="0.00" end="7360.00" id="myEdges">
        <edge id="1" sampledSeconds="269831.10" traveltime="197.36" overlapTraveltime="202.56" density="183.31" occupancy="45.32" waitingTime="3438.00" speed="1.01" departed="1390" arrived="0" entered="0" left="1344" laneChangedFrom="62" laneChangedTo="62"/>
        <edge id="2" sampledSeconds="310410.61" traveltime="228.43" overlapTraveltime="235.39" density="200.00" occupancy="51.18" waitingTime="2735.95" speed="0.87" departed="0" arrived="0" entered="1344" left="1296" laneChangedFrom="83" laneChangedTo="83"/>
        <edge id="3" sampledSeconds="164139.40" traveltime="121.51" overlapTraveltime="127.87" density="200.00" occupancy="57.40" waitingTime="3849.00" speed="0.77" departed="0" arrived="0" entered="1296" left="1273" laneChangedFrom="18" laneChangedTo="18"/>
        <edge id="4" sampledSeconds="42897.49" traveltime="33.35" overlapTraveltime="34.48" density="54.45" occupancy="12.08" waitingTime="0.00" speed="3.25" departed="0" arrived="1268" entered="1273" left="0" laneChangedFrom="136" laneChangedTo="136"/>
    </interval>
</meandata>
