<?xml version="1.0" encoding="UTF-8"?>

<!-- generated on Mon Aug 19 21:33:47 2019 by SUMO Version 0.28.0
<?xml version="1.0" encoding="UTF-8"?>

<configuration xmlns:xsi="http://www.w3.org/2001/XMLSchema-instance" xsi:noNamespaceSchemaLocation="http://sumo.dlr.de/xsd/sumoConfiguration.xsd">

    <input>
        <net-file value="./comAcostamento/aggressive/base.net.xml"/>
        <route-files value="./comAcostamento/aggressive/base.rou.xml"/>
        <additional-files value="./comAcostamento/aggressive/20600/additional20600.xml"/>
    </input>

    <time>
        <begin value="0"/>
        <end value="20600"/>
    </time>

</configuration>
-->

<meandata xmlns:xsi="http://www.w3.org/2001/XMLSchema-instance" xsi:noNamespaceSchemaLocation="http://sumo.dlr.de/xsd/meandata_file.xsd">
    <interval begin="0.00" end="20600.00" id="myEdges">
        <edge id="1" sampledSeconds="644772.80" traveltime="188.53" overlapTraveltime="193.62" density="157.68" occupancy="39.42" waitingTime="63934.33" speed="1.05" departed="3434" arrived="0" entered="0" left="3397" laneChangedFrom="163" laneChangedTo="163"/>
        <edge id="2" sampledSeconds="1107452.74" traveltime="323.60" overlapTraveltime="329.07" density="272.89" occupancy="45.48" waitingTime="304530.76" speed="0.61" departed="0" arrived="0" entered="3396" left="3335" laneChangedFrom="1208" laneChangedTo="1208"/>
        <edge id="3" sampledSeconds="377603.99" traveltime="107.23" overlapTraveltime="113.59" density="200.42" occupancy="50.10" waitingTime="8569.00" speed="0.85" departed="0" arrived="0" entered="3333" left="3315" laneChangedFrom="70" laneChangedTo="70"/>
        <edge id="4" sampledSeconds="112183.35" traveltime="33.40" overlapTraveltime="34.52" density="50.88" occupancy="12.72" waitingTime="0.00" speed="3.25" departed="0" arrived="3310" entered="3315" left="0" laneChangedFrom="393" laneChangedTo="393"/>
    </interval>
</meandata>
