<?xml version="1.0" encoding="UTF-8"?>

<!-- generated on Tue Aug 20 02:59:45 2019 by SUMO Version 0.28.0
<?xml version="1.0" encoding="UTF-8"?>

<configuration xmlns:xsi="http://www.w3.org/2001/XMLSchema-instance" xsi:noNamespaceSchemaLocation="http://sumo.dlr.de/xsd/sumoConfiguration.xsd">

    <input>
        <net-file value="./comAcostamento/aggressive/base.net.xml"/>
        <route-files value="./comAcostamento/aggressive/base.rou.xml"/>
        <additional-files value="./comAcostamento/aggressive/33120/additional33120.xml"/>
    </input>

    <time>
        <begin value="0"/>
        <end value="33120"/>
    </time>

</configuration>
-->

<meandata xmlns:xsi="http://www.w3.org/2001/XMLSchema-instance" xsi:noNamespaceSchemaLocation="http://sumo.dlr.de/xsd/meandata_file.xsd">
    <interval begin="0.00" end="33120.00" id="myEdges">
        <edge id="1" sampledSeconds="1132920.64" traveltime="207.91" overlapTraveltime="213.50" density="172.33" occupancy="43.08" waitingTime="114045.75" speed="0.95" departed="5461" arrived="0" entered="0" left="5424" laneChangedFrom="168" laneChangedTo="168"/>
        <edge id="2" sampledSeconds="1873448.00" traveltime="341.82" overlapTraveltime="347.39" density="287.13" occupancy="47.86" waitingTime="514078.42" speed="0.58" departed="0" arrived="0" entered="5423" left="5362" laneChangedFrom="1721" laneChangedTo="1721"/>
        <edge id="3" sampledSeconds="613007.85" traveltime="108.18" overlapTraveltime="114.53" density="202.37" occupancy="50.59" waitingTime="13846.00" speed="0.84" departed="0" arrived="0" entered="5361" left="5344" laneChangedFrom="70" laneChangedTo="70"/>
        <edge id="4" sampledSeconds="180762.71" traveltime="33.38" overlapTraveltime="34.50" density="50.99" occupancy="12.75" waitingTime="0.00" speed="3.25" departed="0" arrived="5338" entered="5344" left="0" laneChangedFrom="624" laneChangedTo="624"/>
    </interval>
</meandata>
