<?xml version="1.0" encoding="UTF-8"?>

<!-- generated on Fri Aug 16 10:25:47 2019 by SUMO Version 0.28.0
<?xml version="1.0" encoding="UTF-8"?>

<configuration xmlns:xsi="http://www.w3.org/2001/XMLSchema-instance" xsi:noNamespaceSchemaLocation="http://sumo.dlr.de/xsd/sumoConfiguration.xsd">

    <input>
        <net-file value="./semAcostamento/lc2013/base.net.xml"/>
        <route-files value="./semAcostamento/lc2013/base.rou.xml"/>
        <additional-files value="./semAcostamento/lc2013/47600/additional47600.xml"/>
    </input>

    <time>
        <begin value="0"/>
        <end value="47600"/>
    </time>

</configuration>
-->

<meandata xmlns:xsi="http://www.w3.org/2001/XMLSchema-instance" xsi:noNamespaceSchemaLocation="http://sumo.dlr.de/xsd/meandata_file.xsd">
    <interval begin="0.00" end="47600.00" id="myEdges">
        <edge id="1" sampledSeconds="2102193.49" traveltime="250.39" overlapTraveltime="256.75" density="220.82" occupancy="55.20" waitingTime="26447.00" speed="0.80" departed="8420" arrived="0" entered="0" left="8374" laneChangedFrom="155" laneChangedTo="155"/>
        <edge id="2" sampledSeconds="2243494.58" traveltime="261.26" overlapTraveltime="268.70" density="235.66" occupancy="58.92" waitingTime="19772.33" speed="0.76" departed="0" arrived="0" entered="8374" left="8326" laneChangedFrom="128" laneChangedTo="128"/>
        <edge id="3" sampledSeconds="1095306.54" traveltime="125.37" overlapTraveltime="131.74" density="247.53" occupancy="61.88" waitingTime="25135.00" speed="0.74" departed="0" arrived="0" entered="8326" left="8304" laneChangedFrom="30" laneChangedTo="30"/>
        <edge id="4" sampledSeconds="280861.21" traveltime="33.37" overlapTraveltime="34.49" density="55.12" occupancy="13.78" waitingTime="0.00" speed="3.25" departed="0" arrived="8298" entered="8304" left="0" laneChangedFrom="864" laneChangedTo="864"/>
    </interval>
</meandata>
