<?xml version="1.0" encoding="UTF-8"?>

<!-- generated on Tue Aug 20 08:51:32 2019 by SUMO Version 0.28.0
<?xml version="1.0" encoding="UTF-8"?>

<configuration xmlns:xsi="http://www.w3.org/2001/XMLSchema-instance" xsi:noNamespaceSchemaLocation="http://sumo.dlr.de/xsd/sumoConfiguration.xsd">

    <input>
        <net-file value="./semAcostamento/aggressive/base.net.xml"/>
        <route-files value="./semAcostamento/aggressive/base.rou.xml"/>
        <additional-files value="./semAcostamento/aggressive/49260/additional49260.xml"/>
    </input>

    <time>
        <begin value="0"/>
        <end value="49260"/>
    </time>

</configuration>
-->

<meandata xmlns:xsi="http://www.w3.org/2001/XMLSchema-instance" xsi:noNamespaceSchemaLocation="http://sumo.dlr.de/xsd/meandata_file.xsd">
    <interval begin="0.00" end="49260.00" id="myEdges">
        <edge id="1" sampledSeconds="1832451.52" traveltime="228.98" overlapTraveltime="234.80" density="186.00" occupancy="46.50" waitingTime="17026.19" speed="0.87" departed="8023" arrived="0" entered="0" left="7985" laneChangedFrom="104" laneChangedTo="104"/>
        <edge id="2" sampledSeconds="1938619.87" traveltime="237.27" overlapTraveltime="243.41" density="196.77" occupancy="49.19" waitingTime="13199.78" speed="0.84" departed="0" arrived="0" entered="7985" left="7945" laneChangedFrom="149" laneChangedTo="149"/>
        <edge id="3" sampledSeconds="950700.85" traveltime="113.44" overlapTraveltime="119.81" density="207.61" occupancy="51.90" waitingTime="21113.47" speed="0.82" departed="0" arrived="0" entered="7945" left="7926" laneChangedFrom="43" laneChangedTo="43"/>
        <edge id="4" sampledSeconds="268674.11" traveltime="33.45" overlapTraveltime="34.57" density="50.95" occupancy="12.74" waitingTime="0.00" speed="3.24" departed="0" arrived="7921" entered="7926" left="0" laneChangedFrom="714" laneChangedTo="714"/>
    </interval>
</meandata>
