<?xml version="1.0" encoding="UTF-8"?>

<!-- generated on Sat Jul 13 23:19:04 2019 by SUMO Version 0.32.0
<?xml version="1.0" encoding="UTF-8"?>

<configuration xmlns:xsi="http://www.w3.org/2001/XMLSchema-instance" xsi:noNamespaceSchemaLocation="http://sumo.dlr.de/xsd/sumoConfiguration.xsd">

    <input>
        <net-file value="./comAcostamento/lc2013/base.net.xml"/>
        <route-files value="./comAcostamento/lc2013/base.rou.xml"/>
        <additional-files value="./comAcostamento/lc2013/8820/additional8820.xml"/>
    </input>

    <time>
        <begin value="0"/>
        <end value="8820"/>
    </time>

</configuration>
-->

<meandata xmlns:xsi="http://www.w3.org/2001/XMLSchema-instance" xsi:noNamespaceSchemaLocation="http://sumo.dlr.de/xsd/meandata_file.xsd">
    <interval begin="0.00" end="8820.00" id="myLanes">
        <edge id="1">
            <lane id="1_0" sampledSeconds="156777.27" traveltime="186.16" overlapTraveltime="190.86" density="89.55" occupancy="44.13" waitingTime="4403.61" speed="1.07" departed="834" arrived="0" entered="0" left="859" laneChangedFrom="18" laneChangedTo="65"/>
            <lane id="1_1" sampledSeconds="156910.65" traveltime="194.60" overlapTraveltime="200.28" density="89.62" occupancy="44.13" waitingTime="3286.93" speed="1.02" departed="836" arrived="0" entered="0" left="766" laneChangedFrom="65" laneChangedTo="18"/>
        </edge>
        <edge id="2">
            <lane id="2_0" sampledSeconds="188266.33" traveltime="376.06" overlapTraveltime="382.48" density="108.35" occupancy="53.36" waitingTime="43355.00" speed="0.53" departed="0" arrived="0" entered="858" left="427" laneChangedFrom="429" laneChangedTo="23"/>
            <lane id="2_1" sampledSeconds="182700.95" traveltime="487.39" overlapTraveltime="493.59" density="105.15" occupancy="52.11" waitingTime="40789.00" speed="0.41" departed="0" arrived="0" entered="1" left="386" laneChangedFrom="89" laneChangedTo="498"/>
            <lane id="2_2" sampledSeconds="178188.84" traveltime="240.42" overlapTraveltime="246.12" density="102.55" occupancy="50.00" waitingTime="4530.32" speed="0.82" departed="0" arrived="0" entered="764" left="737" laneChangedFrom="69" laneChangedTo="66"/>
        </edge>
        <edge id="3">
            <lane id="3_0" sampledSeconds="96896.20" traveltime="118.04" overlapTraveltime="124.47" density="120.12" occupancy="57.59" waitingTime="2238.00" speed="0.77" departed="0" arrived="0" entered="812" left="760" laneChangedFrom="41" laneChangedTo="0"/>
            <lane id="3_1" sampledSeconds="97372.12" traveltime="121.88" overlapTraveltime="128.15" density="120.71" occupancy="57.41" waitingTime="2135.00" speed="0.75" departed="0" arrived="0" entered="738" left="768" laneChangedFrom="0" laneChangedTo="41"/>
        </edge>
        <edge id="4">
            <lane id="4_0" sampledSeconds="29306.04" traveltime="32.04" overlapTraveltime="33.07" density="31.04" occupancy="13.94" waitingTime="0.00" speed="3.39" departed="0" arrived="1043" entered="760" left="0" laneChangedFrom="1" laneChangedTo="287"/>
            <lane id="4_1" sampledSeconds="22186.70" traveltime="35.11" overlapTraveltime="36.34" density="23.50" occupancy="10.25" waitingTime="0.00" speed="3.08" departed="0" arrived="479" entered="768" left="0" laneChangedFrom="287" laneChangedTo="1"/>
        </edge>
    </interval>
</meandata>
